{
	"configurations" : 
	[
		{
			"directories" : 
			[
				{
					"build" : ".",
					"childIndexes" : 
					[
						1
					],
					"hasInstallRule" : true,
					"jsonFile" : "directory-.-Debug-d0094a50bb2071803777.json",
					"minimumCMakeVersion" : 
					{
						"string" : "3.23"
					},
					"projectIndex" : 0,
					"source" : ".",
					"targetIndexes" : 
					[
						0
					]
				},
				{
					"build" : "googletest-main",
					"childIndexes" : 
					[
						2
					],
					"hasInstallRule" : true,
					"jsonFile" : "directory-googletest-main-Debug-592c0c85abf1308f476e.json",
					"minimumCMakeVersion" : 
					{
						"string" : "3.13"
					},
					"parentIndex" : 0,
					"projectIndex" : 1,
					"source" : "googletest-main"
				},
				{
					"build" : "googletest-main/googlemock",
					"childIndexes" : 
					[
						3
					],
					"hasInstallRule" : true,
					"jsonFile" : "directory-googletest-main.googlemock-Debug-902cf67ce6cb6f5faea1.json",
					"minimumCMakeVersion" : 
					{
						"string" : "3.13"
					},
					"parentIndex" : 1,
					"projectIndex" : 2,
					"source" : "googletest-main/googlemock",
					"targetIndexes" : 
					[
						1,
						2
					]
				},
				{
					"build" : "googletest-main/googletest",
					"hasInstallRule" : true,
					"jsonFile" : "directory-googletest-main.googletest-Debug-4e76eeaaf09ae5fa9fc2.json",
					"minimumCMakeVersion" : 
					{
						"string" : "3.13"
					},
					"parentIndex" : 2,
					"projectIndex" : 3,
					"source" : "googletest-main/googletest",
					"targetIndexes" : 
					[
						3,
						4
					]
				}
			],
			"name" : "Debug",
			"projects" : 
			[
				{
					"childIndexes" : 
					[
						1
					],
					"directoryIndexes" : 
					[
						0
					],
					"name" : "Progetto",
					"targetIndexes" : 
					[
						0
					]
				},
				{
					"childIndexes" : 
					[
						2
					],
					"directoryIndexes" : 
					[
						1
					],
					"name" : "googletest-distribution",
					"parentIndex" : 0
				},
				{
					"childIndexes" : 
					[
						3
					],
					"directoryIndexes" : 
					[
						2
					],
					"name" : "gmock",
					"parentIndex" : 1,
					"targetIndexes" : 
					[
						1,
						2
					]
				},
				{
					"directoryIndexes" : 
					[
						3
					],
					"name" : "gtest",
					"parentIndex" : 2,
					"targetIndexes" : 
					[
						3,
						4
					]
				}
			],
			"targets" : 
			[
				{
					"directoryIndex" : 0,
					"id" : "Progetto::@6890427a1f51a3e7e1df",
					"jsonFile" : "target-Progetto-Debug-5433638be4af9f00969f.json",
					"name" : "Progetto",
					"projectIndex" : 0
				},
				{
					"directoryIndex" : 2,
					"id" : "gmock::@4a5e0150e0633770e005",
					"jsonFile" : "target-gmock-Debug-bd5955b7d983d1e67cac.json",
					"name" : "gmock",
					"projectIndex" : 2
				},
				{
					"directoryIndex" : 2,
					"id" : "gmock_main::@4a5e0150e0633770e005",
					"jsonFile" : "target-gmock_main-Debug-35f2f3aadb06f049a3c0.json",
					"name" : "gmock_main",
					"projectIndex" : 2
				},
				{
					"directoryIndex" : 3,
					"id" : "gtest::@34684d3ffa30950a49d5",
					"jsonFile" : "target-gtest-Debug-38c5c77e6b7f7a2c44d7.json",
					"name" : "gtest",
					"projectIndex" : 3
				},
				{
					"directoryIndex" : 3,
					"id" : "gtest_main::@34684d3ffa30950a49d5",
					"jsonFile" : "target-gtest_main-Debug-0635e017eb44c428e1eb.json",
					"name" : "gtest_main",
					"projectIndex" : 3
				}
			]
		}
	],
	"kind" : "codemodel",
	"paths" : 
	{
		"build" : "C:/Users/ft001/Desktop/Progetto/cmake-build-debug",
		"source" : "C:/Users/ft001/Desktop/Progetto"
	},
	"version" : 
	{
		"major" : 2,
		"minor" : 4
	}
}
